django_migrations_formatter/__init__.py
django_migrations_formatter/apps.py
django_migrations_formatter-1.0.0.dist-info/LICENSE
django_migrations_formatter-1.0.0.dist-info/METADATA
django_migrations_formatter-1.0.0.dist-info/WHEEL
django_migrations_formatter-1.0.0.dist-info/top_level.txt
django_migrations_formatter-1.0.0.dist-info/RECORD
