Metadata-Version: 2.1
Name: django-migrations-formatter
Version: 1.0.0
Summary: A Django library to automatically format your migrations.
Home-page: https://github.com/MarkusH/django-migrations-formatter
Author: Markus Holtermann
Author-email: info@markusholtermann.eu
License: BSD
Project-URL: CI, https://github.com/MarkusH/django-migrations-formatter/actions
Project-URL: Changelog, https://github.com/MarkusH/django-migrations-formatter/blob/main/CHANGELOG.md
Project-URL: Issues, https://github.com/MarkusH/django-migrations-formatter/issues
Platform: UNKNOWN
Classifier: Development Status :: 3 - Alpha
Classifier: Environment :: Web Environment
Classifier: Framework :: Django
Classifier: Framework :: Django :: 2.2
Classifier: Framework :: Django :: 3.2
Classifier: Framework :: Django :: 4.0
Classifier: Intended Audience :: Developers
Classifier: License :: OSI Approved :: BSD License
Classifier: Operating System :: OS Independent
Classifier: Programming Language :: Python
Classifier: Programming Language :: Python :: 3
Classifier: Programming Language :: Python :: 3.7
Classifier: Programming Language :: Python :: 3.8
Classifier: Programming Language :: Python :: 3.9
Classifier: Programming Language :: Python :: 3.10
Requires-Python: >=3.7
License-File: LICENSE
Provides-Extra: black
Requires-Dist: black (>=22.1.0) ; extra == 'black'
Provides-Extra: dev
Requires-Dist: pre-commit ; extra == 'dev'
Provides-Extra: isort
Requires-Dist: isort ; extra == 'isort'
Provides-Extra: test
Requires-Dist: coverage[toml] (<7,>=6) ; extra == 'test'
Requires-Dist: Django ; extra == 'test'
